formatters/__init__.py
formatters/excel.py
formatters/html.py
formatters/py.typed
dataframe_formatters-0.0.2.dist-info/LICENSE
dataframe_formatters-0.0.2.dist-info/METADATA
dataframe_formatters-0.0.2.dist-info/WHEEL
dataframe_formatters-0.0.2.dist-info/top_level.txt
dataframe_formatters-0.0.2.dist-info/RECORD
