Metadata-Version: 2.1
Name: dataframe-formatters
Version: 0.0.2
Requires-Python: >=3.10
License-File: LICENSE
Requires-Dist: pandas <3.0.0,>=2.0.0
Requires-Dist: openpyxl <4.0.0,>=3.1.2
